igel/__init__.py
igel/__main__.py
igel/auto/__init__.py
igel/auto/cnn.py
igel/auto/defaults.py
igel/auto/example.py
igel/auto/models.py
igel/configs.py
igel/constants.py
igel/data.py
igel/extras/__init__.py
igel/extras/disclaimer.md
igel/extras/kmedians.py
igel/extras/kmedoids.py
igel/hyperparams.py
igel/igel.py
igel/preprocessing.py
igel/servers/__init__.py
igel/servers/fastapi_server.py
igel/servers/helper.py
igel/utils.py
igel-1.0.0.dist-info/entry_points.txt
igel-1.0.0.dist-info/LICENSE
igel-1.0.0.dist-info/WHEEL
igel-1.0.0.dist-info/METADATA
igel-1.0.0.dist-info/RECORD
