Metadata-Version: 2.1
Name: igel
Version: 1.0.0
Summary: a delightful machine learning tool that allows you to train, test and use models without writing code
License: MIT
Author: nidhal baccouri
Author-email: nidhalbacc@gmail.com
Requires-Python: >=3.8,<4.0
Classifier: Development Status :: 4 - Beta
Classifier: Intended Audience :: Developers
Classifier: License :: OSI Approved :: MIT License
Classifier: Operating System :: OS Independent
Classifier: Programming Language :: Python :: 3
Classifier: Programming Language :: Python :: 3.10
Classifier: Programming Language :: Python :: 3.8
Classifier: Programming Language :: Python :: 3.9
Classifier: Topic :: Software Development :: Libraries :: Python Modules
Requires-Dist: Pillow (>=8.3.2,<9.0.0)
Requires-Dist: PyYAML (==5.3.1)
Requires-Dist: autokeras (>=1.0.16,<2.0.0)
Requires-Dist: click (>=8.0.1,<9.0.0)
Requires-Dist: fastapi (>=0.65.2,<0.66.0)
Requires-Dist: importlib_metadata (>=1.6.0,<2.0.0); python_version >= "3.8"
Requires-Dist: joblib (>=0.16.0,<0.17.0)
Requires-Dist: pandas (==1.1.1)
Requires-Dist: scikit-learn (==0.23.2)
Requires-Dist: uvicorn (>=0.14.0,<0.15.0)
